Workbook

Sheet Revenue Build
B1: South LA Community Carshare
B2: Revenue Build and Key Assumptions
B4: Base Assumptions | D4: 2026
B5: Fleet size (vehicles) | C5: 10 | D5: Jan | E5: Feb | F5: Mar | G5: Apr | H5: May | I5: Jun | J5: Jul | K5: Aug | L5: Sep | M5: Oct | N5: Nov. | O5: Dec. | P5: Total
B6: Avg. billable hours / day / vehicle | C6: 5
B7: Planning days billed / month | C7: 30
B8: Average hourly rate ($/hour) | C8: 11
B9: Active members in base case | C9: 0
B10: Membership fee ($/month) | C10: 5
B11: Insurance per vehicle / year | C11: 3000
B12: Maintenance per vehicle / year | C12: 1200
B13: Cleaning & minor repairs / vehicle / year | C13: 600
B14: Depreciation per vehicle / year | C14: 4000
B15: Software / booking platform / year | C15: 3000
B16: Parking / storage / year | C16: 12000
B18: Revenue Build
B19: Booking revenue | D19: =$C$5*$C$6*$C$7*$C$8 -> 16500 | E19: =$C$5*$C$6*$C$7*$C$8 -> 16500 | F19: =$C$5*$C$6*$C$7*$C$8 -> 16500 | G19: =$C$5*$C$6*$C$7*$C$8 -> 16500 | H19: =$C$5*$C$6*$C$7*$C$8 -> 16500 | I19: =$C$5*$C$6*$C$7*$C$8 -> 16500 | J19: =$C$5*$C$6*$C$7*$C$8 -> 16500 | K19: =$C$5*$C$6*$C$7*$C$8 -> 16500 | ... O19: =$C$5*$C$6*$C$7*$C$8 -> 16500 | P19: =SUM(D19:O19) -> 198000
B20: Membership revenue | D20: =$C$9*$C$10 -> 0 | E20: =$C$9*$C$10 -> 0 | F20: =$C$9*$C$10 -> 0 | G20: =$C$9*$C$10 -> 0 | H20: =$C$9*$C$10 -> 0 | I20: =$C$9*$C$10 -> 0 | J20: =$C$9*$C$10 -> 0 | K20: =$C$9*$C$10 -> 0 | ... O20: =$C$9*$C$10 -> 0 | P20: =SUM(D20:O20) -> 0
B21: Total revenue | D21: =D19+D20 -> 16500 | E21: =E19+E20 -> 16500 | F21: =F19+F20 -> 16500 | G21: =G19+G20 -> 16500 | H21: =H19+H20 -> 16500 | I21: =I19+I20 -> 16500 | J21: =J19+J20 -> 16500 | K21: =K19+K20 -> 16500 | ... O21: =O19+O20 -> 16500 | P21: =SUM(D21:O21) -> 198000
B22: Direct Vehicle Operating Costs
B23: Insurance | D23: =($C$11*$C$5)/12 -> 2500 | E23: =($C$11*$C$5)/12 -> 2500 | F23: =($C$11*$C$5)/12 -> 2500 | G23: =($C$11*$C$5)/12 -> 2500 | H23: =($C$11*$C$5)/12 -> 2500 | I23: =($C$11*$C$5)/12 -> 2500 | J23: =($C$11*$C$5)/12 -> 2500 | K23: =($C$11*$C$5)/12 -> 2500 | ... O23: =($C$11*$C$5)/12 -> 2500 | P23: =SUM(D23:O23) -> 30000
B24: Maintenance | D24: =($C$12*$C$5)/12 -> 1000 | E24: =($C$12*$C$5)/12 -> 1000 | F24: =($C$12*$C$5)/12 -> 1000 | G24: =($C$12*$C$5)/12 -> 1000 | H24: =($C$12*$C$5)/12 -> 1000 | I24: =($C$12*$C$5)/12 -> 1000 | J24: =($C$12*$C$5)/12 -> 1000 | K24: =($C$12*$C$5)/12 -> 1000 | ... O24: =($C$12*$C$5)/12 -> 1000 | P24: =SUM(D24:O24) -> 12000
B25: Cleaning & minor repairs | D25: =($C$13*$C$5)/12 -> 500 | E25: =($C$13*$C$5)/12 -> 500 | F25: =($C$13*$C$5)/12 -> 500 | G25: =($C$13*$C$5)/12 -> 500 | H25: =($C$13*$C$5)/12 -> 500 | I25: =($C$13*$C$5)/12 -> 500 | J25: =($C$13*$C$5)/12 -> 500 | K25: =($C$13*$C$5)/12 -> 500 | ... O25: =($C$13*$C$5)/12 -> 500 | P25: =SUM(D25:O25) -> 6000
B26: Depreciation | D26: =($C$14*$C$5)/12 -> 3333.3333 | E26: =($C$14*$C$5)/12 -> 3333.3333 | F26: =($C$14*$C$5)/12 -> 3333.3333 | G26: =($C$14*$C$5)/12 -> 3333.3333 | H26: =($C$14*$C$5)/12 -> 3333.3333 | I26: =($C$14*$C$5)/12 -> 3333.3333 | J26: =($C$14*$C$5)/12 -> 3333.3333 | K26: =($C$14*$C$5)/12 -> 3333.3333 | ... O26: =($C$14*$C$5)/12 -> 3333.3333 | P26: =SUM(D26:O26) -> 40000
B27: Total direct vehicle operating costs | D27: =SUM(D23:D26) -> 7333.3333 | E27: =SUM(E23:E26) -> 7333.3333 | F27: =SUM(F23:F26) -> 7333.3333 | G27: =SUM(G23:G26) -> 7333.3333 | H27: =SUM(H23:H26) -> 7333.3333 | I27: =SUM(I23:I26) -> 7333.3333 | J27: =SUM(J23:J26) -> 7333.3333 | K27: =SUM(K23:K26) -> 7333.3333 | ... O27: =SUM(O23:O26) -> 7333.3333 | P27: =SUM(D27:O27) -> 88000
B28: Operating Expenses
B29: Software / booking platform | D29: =$C$15/12 -> 250 | E29: =$C$15/12 -> 250 | F29: =$C$15/12 -> 250 | G29: =$C$15/12 -> 250 | H29: =$C$15/12 -> 250 | I29: =$C$15/12 -> 250 | J29: =$C$15/12 -> 250 | K29: =$C$15/12 -> 250 | ... O29: =$C$15/12 -> 250 | P29: =SUM(D29:O29) -> 3000
B30: Parking / storage | D30: =$C$16/12 -> 1000 | E30: =$C$16/12 -> 1000 | F30: =$C$16/12 -> 1000 | G30: =$C$16/12 -> 1000 | H30: =$C$16/12 -> 1000 | I30: =$C$16/12 -> 1000 | J30: =$C$16/12 -> 1000 | K30: =$C$16/12 -> 1000 | ... O30: =$C$16/12 -> 1000 | P30: =SUM(D30:O30) -> 12000
B31: Total operating expenses | D31: =SUM(D29:D30) -> 1250 | E31: =SUM(E29:E30) -> 1250 | F31: =SUM(F29:F30) -> 1250 | G31: =SUM(G29:G30) -> 1250 | H31: =SUM(H29:H30) -> 1250 | I31: =SUM(I29:I30) -> 1250 | J31: =SUM(J29:J30) -> 1250 | K31: =SUM(K29:K30) -> 1250 | ... O31: =SUM(O29:O30) -> 1250 | P31: =SUM(D31:O31) -> 15000
B33: Gross profit | D33: =D21-D27 -> 9166.6667 | E33: =E21-E27 -> 9166.6667 | F33: =F21-F27 -> 9166.6667 | G33: =G21-G27 -> 9166.6667 | H33: =H21-H27 -> 9166.6667 | I33: =I21-I27 -> 9166.6667 | J33: =J21-J27 -> 9166.6667 | K33: =K21-K27 -> 9166.6667 | ... O33: =O21-O27 -> 9166.6667 | P33: =SUM(D33:O33) -> 110000
B34: Net profit (loss) | D34: =D33-D31 -> 7916.6667 | E34: =E33-E31 -> 7916.6667 | F34: =F33-F31 -> 7916.6667 | G34: =G33-G31 -> 7916.6667 | H34: =H33-H31 -> 7916.6667 | I34: =I33-I31 -> 7916.6667 | J34: =J33-J31 -> 7916.6667 | K34: =K33-K31 -> 7916.6667 | ... O34: =O33-O31 -> 7916.6667 | P34: =SUM(D34:O34) -> 95000
B37: Key outputs
B38: Expected annual revenue | C38: =P21 -> 198000
B39: Expected annual direct operating costs | C39: =P27 -> 88000
B40: Expected annual operating expenses | C40: =P31 -> 15000
B41: Expected annual net profit | C41: =P34 -> 95000
B42: Net profit margin | C42: =P34/P21 -> 0.47979798
B43: Revenue per vehicle / year | C43: =P21/$C$5 -> 19800

Sheet Projections
A1: South LA Community Carshare
A2: Projected Profit and Loss Statement
D4: 2026
D5: Jan | E5: Feb | F5: Mar | G5: Apr | H5: May | I5: Jun | J5: Jul | K5: Aug | L5: Sep | M5: Oct | N5: Nov. | O5: Dec. | P5: Total | Q5: %
A6: Total revenue | D6: ='Revenue Build'!D21 -> 16500 | E6: ='Revenue Build'!E21 -> 16500 | F6: ='Revenue Build'!F21 -> 16500 | G6: ='Revenue Build'!G21 -> 16500 | H6: ='Revenue Build'!H21 -> 16500 | I6: ='Revenue Build'!I21 -> 16500 | J6: ='Revenue Build'!J21 -> 16500 | K6: ='Revenue Build'!K21 -> 16500 | ... O6: ='Revenue Build'!O21 -> 16500 | P6: =SUM(D6:O6) -> 198000 | Q6: =1 -> 1
A8: Less Direct Vehicle Operating Costs | D8: ='Revenue Build'!D27 -> 7333.3333 | E8: ='Revenue Build'!E27 -> 7333.3333 | F8: ='Revenue Build'!F27 -> 7333.3333 | G8: ='Revenue Build'!G27 -> 7333.3333 | H8: ='Revenue Build'!H27 -> 7333.3333 | I8: ='Revenue Build'!I27 -> 7333.3333 | J8: ='Revenue Build'!J27 -> 7333.3333 | K8: ='Revenue Build'!K27 -> 7333.3333 | ... O8: ='Revenue Build'!O27 -> 7333.3333 | P8: =SUM(D8:O8) -> 88000 | Q8: =IF($P$6=0,0,P8/$P$6) -> 0.44444444
A9: Gross Profit | D9: =D6-D8 -> 9166.6667 | E9: =E6-E8 -> 9166.6667 | F9: =F6-F8 -> 9166.6667 | G9: =G6-G8 -> 9166.6667 | H9: =H6-H8 -> 9166.6667 | I9: =I6-I8 -> 9166.6667 | J9: =J6-J8 -> 9166.6667 | K9: =K6-K8 -> 9166.6667 | ... O9: =O6-O8 -> 9166.6667 | P9: =SUM(D9:O9) -> 110000 | Q9: =IF($P$6=0,0,P9/$P$6) -> 0.55555556
B11: Operating Expenses
B12: Software / booking platform | D12: ='Revenue Build'!D29 -> 250 | E12: ='Revenue Build'!E29 -> 250 | F12: ='Revenue Build'!F29 -> 250 | G12: ='Revenue Build'!G29 -> 250 | H12: ='Revenue Build'!H29 -> 250 | I12: ='Revenue Build'!I29 -> 250 | J12: ='Revenue Build'!J29 -> 250 | K12: ='Revenue Build'!K29 -> 250 | ... O12: ='Revenue Build'!O29 -> 250 | P12: =SUM(D12:O12) -> 3000 | Q12: =IF($P$6=0,0,P12/$P$6) -> 0.015151515
B13: Parking / storage | D13: ='Revenue Build'!D30 -> 1000 | E13: ='Revenue Build'!E30 -> 1000 | F13: ='Revenue Build'!F30 -> 1000 | G13: ='Revenue Build'!G30 -> 1000 | H13: ='Revenue Build'!H30 -> 1000 | I13: ='Revenue Build'!I30 -> 1000 | J13: ='Revenue Build'!J30 -> 1000 | K13: ='Revenue Build'!K30 -> 1000 | ... O13: ='Revenue Build'!O30 -> 1000 | P13: =SUM(D13:O13) -> 12000 | Q13: =IF($P$6=0,0,P13/$P$6) -> 0.060606061
B14: Customer support / admin | D14: 0 | E14: 0 | F14: 0 | G14: 0 | H14: 0 | I14: 0 | J14: 0 | K14: 0 | L14: 0 | M14: 0 | N14: 0 | O14: 0 | P14: =SUM(D14:O14) -> 0 | Q14: =IF($P$6=0,0,P14/$P$6) -> 0
B15: Legal / accounting reserve | D15: 0 | E15: 0 | F15: 0 | G15: 0 | H15: 0 | I15: 0 | J15: 0 | K15: 0 | L15: 0 | M15: 0 | N15: 0 | O15: 0 | P15: =SUM(D15:O15) -> 0 | Q15: =IF($P$6=0,0,P15/$P$6) -> 0
A32: Total Expenses | D32: =SUM(D12:D31) -> 1250 | E32: =SUM(E12:E31) -> 1250 | F32: =SUM(F12:F31) -> 1250 | G32: =SUM(G12:G31) -> 1250 | H32: =SUM(H12:H31) -> 1250 | I32: =SUM(I12:I31) -> 1250 | J32: =SUM(J12:J31) -> 1250 | K32: =SUM(K12:K31) -> 1250 | ... O32: =SUM(O12:O31) -> 1250 | P32: =SUM(D32:O32) -> 15000 | Q32: =IF($P$6=0,0,P32/$P$6) -> 0.075757576
A33: Net Profit (Loss) | D33: =D9-D32 -> 7916.6667 | E33: =E9-E32 -> 7916.6667 | F33: =F9-F32 -> 7916.6667 | G33: =G9-G32 -> 7916.6667 | H33: =H9-H32 -> 7916.6667 | I33: =I9-I32 -> 7916.6667 | J33: =J9-J32 -> 7916.6667 | K33: =K9-K32 -> 7916.6667 | ... O33: =O9-O32 -> 7916.6667 | P33: =SUM(D33:O33) -> 95000 | Q33: =IF($P$6=0,0,P33/$P$6) -> 0.47979798
A36: South LA Community Carshare
A37: Operating KPI Summary
C39: Base Case
C40: Metric | D40: Result
B41: Vehicles in fleet | D41: ='Revenue Build'!$C$5 -> 10
B42: Avg. billable hours / day / vehicle | D42: ='Revenue Build'!$C$6 -> 5
B43: Revenue per vehicle / month | D43: =P6/D41/12 -> 1650
B44: Revenue per vehicle / year | D44: =P6/D41 -> 19800
B45: Net profit margin | D45: =P33/P6 -> 0.47979798
B46: Break-even billable hours / day / vehicle | D46: ='breakeven analysis'!C13 -> 2.6010101
B47: Expected annual revenue | D47: =P6 -> 198000
B48: Expected annual net profit | D48: =P33 -> 95000

Sheet breakeven analysis
A1: South LA Community Carshare
A2: Breakeven Analysis
B3: Assumptions:
B4: Fleet size remains fixed at the 10-vehicle base case
B5: Average hourly rate remains $11 per hour
B6: Base case assumes no membership revenue
B8: Annual planning days = 12 months x 30 billed days / month
B10: Annual direct vehicle operating costs | C10: ='Revenue Build'!P27 -> 88000
B11: Annual operating expenses | C11: ='Revenue Build'!P31 -> 15000
B12: Total annual cost base | C12: =C10+C11 -> 103000
B13: Break-even billable hours / day / vehicle | C13: =C12/('Revenue Build'!$C$5*12*'Revenue Build'!$C$7*'Revenue Build'!$C$8) -> 2.6010101
B14: Base-case billable hours / day / vehicle | C14: ='Revenue Build'!$C$6 -> 5
B15: Revenue cushion above break-even | C15: =C14-C13 -> 2.3989899
A18: Utilization sensitivity
B19: Hours / day / vehicle | C19: 1 | D19: 1.5 | E19: 2 | F19: 2.5 | G19: 3 | H19: 3.5 | I19: 4 | J19: 4.5 | K19: 5 | L19: 5.5 | M19: 6 | N19: 6.5 | O19: Base | P19: %
B20: Fleet size | C20: ='Revenue Build'!$C$5 -> 10
B21: Hourly rate | C21: ='Revenue Build'!$C$8 -> 11
B23: Annual revenue | C23: =C19*'Revenue Build'!$C$5*12*'Revenue Build'!$C$7*'Revenue Build'!$C$8 -> 39600 | D23: =D19*'Revenue Build'!$C$5*12*'Revenue Build'!$C$7*'Revenue Build'!$C$8 -> 59400 | E23: =E19*'Revenue Build'!$C$5*12*'Revenue Build'!$C$7*'Revenue Build'!$C$8 -> 79200 | F23: =F19*'Revenue Build'!$C$5*12*'Revenue Build'!$C$7*'Revenue Build'!$C$8 -> 99000 | G23: =G19*'Revenue Build'!$C$5*12*'Revenue Build'!$C$7*'Revenue Build'!$C$8 -> 118800 | H23: =H19*'Revenue Build'!$C$5*12*'Revenue Build'!$C$7*'Revenue Build'!$C$8 -> 138600 | I23: =I19*'Revenue Build'!$C$5*12*'Revenue Build'!$C$7*'Revenue Build'!$C$8 -> 158400 | J23: =J19*'Revenue Build'!$C$5*12*'Revenue Build'!$C$7*'Revenue Build'!$C$8 -> 178200 | ... N23: =N19*'Revenue Build'!$C$5*12*'Revenue Build'!$C$7*'Revenue Build'!$C$8 -> 257400 | O23: ='Revenue Build'!P21 -> 198000 | P23: =1 -> 1
B25: Less Direct Vehicle Operating Costs | C25: ='Revenue Build'!P27 -> 88000 | D25: ='Revenue Build'!P27 -> 88000 | E25: ='Revenue Build'!P27 -> 88000 | F25: ='Revenue Build'!P27 -> 88000 | G25: ='Revenue Build'!P27 -> 88000 | H25: ='Revenue Build'!P27 -> 88000 | I25: ='Revenue Build'!P27 -> 88000 | J25: ='Revenue Build'!P27 -> 88000 | K25: ='Revenue Build'!P27 -> 88000 | L25: ='Revenue Build'!P27 -> 88000 | M25: ='Revenue Build'!P27 -> 88000 | N25: ='Revenue Build'!P27 -> 88000 | O25: ='Revenue Build'!P27 -> 88000 | P25: =O25/O23 -> 0.44444444
B26: Gross Profit | C26: =C23-C25 -> -48400 | D26: =D23-D25 -> -28600 | E26: =E23-E25 -> -8800 | F26: =F23-F25 -> 11000 | G26: =G23-G25 -> 30800 | H26: =H23-H25 -> 50600 | I26: =I23-I25 -> 70400 | J26: =J23-J25 -> 90200 | ... O26: =O23-O25 -> 110000 | P26: =O26/O23 -> 0.55555556
B28: Expenses
B29: Software / booking platform | C29: ='Revenue Build'!P29 -> 3000 | D29: ='Revenue Build'!P29 -> 3000 | E29: ='Revenue Build'!P29 -> 3000 | F29: ='Revenue Build'!P29 -> 3000 | G29: ='Revenue Build'!P29 -> 3000 | H29: ='Revenue Build'!P29 -> 3000 | I29: ='Revenue Build'!P29 -> 3000 | J29: ='Revenue Build'!P29 -> 3000 | K29: ='Revenue Build'!P29 -> 3000 | L29: ='Revenue Build'!P29 -> 3000 | M29: ='Revenue Build'!P29 -> 3000 | N29: ='Revenue Build'!P29 -> 3000 | O29: ='Revenue Build'!P29 -> 3000 | P29: =O29/O23 -> 0.015151515
B30: Parking / storage | C30: ='Revenue Build'!P30 -> 12000 | D30: ='Revenue Build'!P30 -> 12000 | E30: ='Revenue Build'!P30 -> 12000 | F30: ='Revenue Build'!P30 -> 12000 | G30: ='Revenue Build'!P30 -> 12000 | H30: ='Revenue Build'!P30 -> 12000 | I30: ='Revenue Build'!P30 -> 12000 | J30: ='Revenue Build'!P30 -> 12000 | K30: ='Revenue Build'!P30 -> 12000 | L30: ='Revenue Build'!P30 -> 12000 | M30: ='Revenue Build'!P30 -> 12000 | N30: ='Revenue Build'!P30 -> 12000 | O30: ='Revenue Build'!P30 -> 12000 | P30: =O30/O23 -> 0.060606061
B46: Total Expenses | C46: =SUM(C29:C45) -> 15000 | D46: =SUM(D29:D45) -> 15000 | E46: =SUM(E29:E45) -> 15000 | F46: =SUM(F29:F45) -> 15000 | G46: =SUM(G29:G45) -> 15000 | H46: =SUM(H29:H45) -> 15000 | I46: =SUM(I29:I45) -> 15000 | J46: =SUM(J29:J45) -> 15000 | ... P46: =SUM(P29:P45) -> 0.075757576
B47: Net Profit (Loss) | C47: =C26-C46 -> -63400 | D47: =D26-D46 -> -43600 | E47: =E26-E46 -> -23800 | F47: =F26-F46 -> -4000 | G47: =G26-G46 -> 15800 | H47: =H26-H46 -> 35600 | I47: =I26-I46 -> 55400 | J47: =J26-J46 -> 75200 | ... O47: =O26-O46 -> 95000 | P47: =O47/O23 -> 0.47979798
